[{"id":0,"demarcheStatutId":"cls","demarchePublique":true,"etapes":[{"date":"2012-05-31","etapeTypeId":"mfr","etapeStatutId":"fai"},{"date":"2012-05-31","etapeTypeId":"mdp","etapeStatutId":"fai"},{"date":"2014-04-23","etapeTypeId":"css","etapeStatutId":"fai"}]},{"id":1,"demarcheStatutId":"rej","demarchePublique":true,"etapes":[{"date":"2021-11-21","etapeTypeId":"mfr","etapeStatutId":"fai","paysId":"GF","surface":1},{"date":"2021-11-22","etapeTypeId":"mdp","etapeStatutId":"fai"},{"date":"2022-05-01","etapeTypeId":"mcr","etapeStatutId":"fav"},{"date":"2022-05-01","etapeTypeId":"asc","etapeStatutId":"fai"},{"date":"2022-05-01","etapeTypeId":"scl","etapeStatutId":"fai"},{"date":"2023-01-17","etapeTypeId":"apd","etapeStatutId":"fav"},{"date":"2023-04-08","etapeTypeId":"spo","etapeStatutId":"fai"},{"date":"2023-04-17","etapeTypeId":"apo","etapeStatutId":"def"},{"date":"2024-02-21","etapeTypeId":"dex","etapeStatutId":"rej","paysId":"GF","surface":1},{"date":"2024-02-27","etapeTypeId":"rpu","etapeStatutId":"fai","paysId":"GF","surface":1},{"date":"2024-03-03","etapeTypeId":"mno","etapeStatutId":"fai"}]},{"id":2,"demarcheStatutId":"rej","demarchePublique":true,"etapes":[{"date":"2019-12-03","etapeTypeId":"mfr","etapeStatutId":"fai"},{"date":"2019-12-03","etapeTypeId":"mdp","etapeStatutId":"fai"},{"date":"2019-12-06","etapeTypeId":"mcr","etapeStatutId":"fav"},{"date":"2022-01-13","etapeTypeId":"dim","etapeStatutId":"rej"}]},{"id":3,"demarcheStatutId":"acc","demarchePublique":true,"etapes":[{"date":"2023-01-15","etapeTypeId":"mfr","etapeStatutId":"fai","paysId":"GF","surface":0.95},{"date":"2023-01-15","etapeTypeId":"mdp","etapeStatutId":"fai"},{"date":"2023-04-09","etapeTypeId":"mcr","etapeStatutId":"fav"},{"date":"2023-04-09","etapeTypeId":"scl","etapeStatutId":"fai"},{"date":"2023-04-09","etapeTypeId":"asc","etapeStatutId":"fai"},{"date":"2023-06-01","etapeTypeId":"apd","etapeStatutId":"fav"},{"date":"2023-06-10","etapeTypeId":"apo","etapeStatutId":"fav"},{"date":"2023-06-30","etapeTypeId":"dex","etapeStatutId":"acc","paysId":"GF","surface":0.95}]},{"id":4,"demarcheStatutId":"rej","demarchePublique":true,"etapes":[{"date":"2019-10-10","etapeTypeId":"mfr","etapeStatutId":"fai","surface":1},{"date":"2019-10-30","etapeTypeId":"mdp","etapeStatutId":"fai"},{"date":"2020-12-29","etapeTypeId":"dim","etapeStatutId":"rej","surface":1}]},{"id":5,"demarcheStatutId":"dep","demarchePublique":false,"etapes":[{"date":"2024-04-27","etapeTypeId":"mfr","etapeStatutId":"fai","paysId":"GF","surface":1},{"date":"2024-04-27","etapeTypeId":"mdp","etapeStatutId":"fai"}]},{"id":6,"demarcheStatutId":"dep","demarchePublique":false,"etapes":[{"date":"2024-05-09","etapeTypeId":"mfr","etapeStatutId":"fai","paysId":"GF","surface":1},{"date":"2024-05-09","etapeTypeId":"mdp","etapeStatutId":"fai"}]},{"id":7,"demarcheStatutId":"dep","demarchePublique":false,"etapes":[{"date":"2024-04-30","etapeTypeId":"mfr","etapeStatutId":"fai","paysId":"GF","surface":0.92},{"date":"2024-04-30","etapeTypeId":"mdp","etapeStatutId":"fai"}]},{"id":8,"demarcheStatutId":"rej","demarchePublique":true,"etapes":[{"date":"2020-02-05","etapeTypeId":"mfr","etapeStatutId":"fai","paysId":"GF","surface":0.91},{"date":"2020-02-24","etapeTypeId":"mdp","etapeStatutId":"fai"},{"date":"2024-05-08","etapeTypeId":"dim","etapeStatutId":"rej","paysId":"GF","surface":0}]},{"id":9,"demarcheStatutId":"des","demarchePublique":true,"etapes":[{"date":"2019-01-15","etapeTypeId":"mfr","etapeStatutId":"fai"},{"date":"2019-01-15","etapeTypeId":"mdp","etapeStatutId":"fai"},{"date":"2021-01-20","etapeTypeId":"des","etapeStatutId":"fai"}]},{"id":10,"demarcheStatutId":"des","demarchePublique":true,"etapes":[{"date":"2022-03-17","etapeTypeId":"mfr","etapeStatutId":"fai","paysId":"GF","surface":1},{"date":"2022-03-17","etapeTypeId":"mdp","etapeStatutId":"fai"},{"date":"2022-11-14","etapeTypeId":"des","etapeStatutId":"fai"}]},{"id":11,"demarcheStatutId":"cls","demarchePublique":true,"etapes":[{"date":"2019-12-23","etapeTypeId":"mfr","etapeStatutId":"fai"},{"date":"2019-12-23","etapeTypeId":"mdp","etapeStatutId":"fai"},{"date":"2022-02-11","etapeTypeId":"css","etapeStatutId":"fai"}]},{"id":12,"demarcheStatutId":"des","demarchePublique":true,"etapes":[{"date":"2022-06-05","etapeTypeId":"mfr","etapeStatutId":"fai","paysId":"GF","surface":0.99},{"date":"2022-06-05","etapeTypeId":"mdp","etapeStatutId":"fai"},{"date":"2023-05-22","etapeTypeId":"des","etapeStatutId":"fai"}]},{"id":13,"demarcheStatutId":"acc","demarchePublique":true,"etapes":[{"date":"2022-02-23","etapeTypeId":"mfr","etapeStatutId":"fai","paysId":"GF","surface":0.99},{"date":"2022-02-27","etapeTypeId":"mdp","etapeStatutId":"fai"},{"date":"2022-10-27","etapeTypeId":"mcr","etapeStatutId":"fav"},{"date":"2022-10-27","etapeTypeId":"asc","etapeStatutId":"fai"},{"date":"2022-10-27","etapeTypeId":"scl","etapeStatutId":"fai"},{"date":"2023-02-18","etapeTypeId":"apd","etapeStatutId":"fav"},{"date":"2023-03-18","etapeTypeId":"apo","etapeStatutId":"fav"},{"date":"2023-03-31","etapeTypeId":"dex","etapeStatutId":"acc","paysId":"GF","surface":0.99}]},{"id":14,"demarcheStatutId":"acc","demarchePublique":true,"etapes":[{"date":"2022-03-13","etapeTypeId":"mfr","etapeStatutId":"fai"},{"date":"2022-03-13","etapeTypeId":"mdp","etapeStatutId":"fai"},{"date":"2022-10-10","etapeTypeId":"mcr","etapeStatutId":"fav"},{"date":"2022-10-10","etapeTypeId":"scl","etapeStatutId":"fai"},{"date":"2022-10-10","etapeTypeId":"asc","etapeStatutId":"fai"},{"date":"2022-11-24","etapeTypeId":"apd","etapeStatutId":"fav"},{"date":"2023-01-03","etapeTypeId":"apo","etapeStatutId":"fav"},{"date":"2023-01-17","etapeTypeId":"dex","etapeStatutId":"acc"}]},{"id":15,"demarcheStatutId":"acc","demarchePublique":true,"etapes":[{"date":"2022-10-25","etapeTypeId":"mfr","etapeStatutId":"fai","paysId":"GF","surface":1.08},{"date":"2022-10-28","etapeTypeId":"mdp","etapeStatutId":"fai"},{"date":"2023-04-07","etapeTypeId":"mcr","etapeStatutId":"fav"},{"date":"2023-04-08","etapeTypeId":"scl","etapeStatutId":"fai"},{"date":"2023-04-08","etapeTypeId":"asc","etapeStatutId":"fai"},{"date":"2023-06-01","etapeTypeId":"apd","etapeStatutId":"fav"},{"date":"2023-06-09","etapeTypeId":"apo","etapeStatutId":"fav"},{"date":"2023-06-29","etapeTypeId":"dex","etapeStatutId":"acc","paysId":"GF","surface":1.08}]},{"id":16,"demarcheStatutId":"rej","demarchePublique":true,"etapes":[{"date":"2016-09-16","etapeTypeId":"mfr","etapeStatutId":"fai"},{"date":"2016-09-16","etapeTypeId":"mdp","etapeStatutId":"fai"},{"date":"2016-11-05","etapeTypeId":"mcr","etapeStatutId":"fav"},{"date":"2016-11-05","etapeTypeId":"asc","etapeStatutId":"fai"},{"date":"2016-11-05","etapeTypeId":"scl","etapeStatutId":"fai"},{"date":"2016-12-24","etapeTypeId":"apd","etapeStatutId":"def"},{"date":"2017-01-01","etapeTypeId":"apo","etapeStatutId":"def"},{"date":"2017-01-14","etapeTypeId":"dex","etapeStatutId":"rej"}]},{"id":17,"demarcheStatutId":"des","demarchePublique":true,"etapes":[{"date":"2017-05-18","etapeTypeId":"mfr","etapeStatutId":"fai"},{"date":"2017-05-18","etapeTypeId":"mdp","etapeStatutId":"fai"},{"date":"2021-06-04","etapeTypeId":"des","etapeStatutId":"fai"}]},{"id":18,"demarcheStatutId":"cls","demarchePublique":true,"etapes":[{"date":"2020-05-03","etapeTypeId":"mfr","etapeStatutId":"fai"},{"date":"2020-05-04","etapeTypeId":"mdp","etapeStatutId":"fai"},{"date":"2021-10-31","etapeTypeId":"css","etapeStatutId":"fai"}]},{"id":19,"demarcheStatutId":"dep","demarchePublique":false,"etapes":[{"date":"2024-05-21","etapeTypeId":"mfr","etapeStatutId":"fai","paysId":"GF","surface":0.99},{"date":"2024-05-21","etapeTypeId":"mdp","etapeStatutId":"fai"}]},{"id":20,"demarcheStatutId":"cls","demarchePublique":true,"etapes":[{"date":"2013-11-12","etapeTypeId":"mfr","etapeStatutId":"fai"},{"date":"2013-11-12","etapeTypeId":"mdp","etapeStatutId":"fai"},{"date":"2015-08-04","etapeTypeId":"css","etapeStatutId":"fai"}]},{"id":21,"demarcheStatutId":"acc","demarchePublique":true,"etapes":[{"date":"2022-04-26","etapeTypeId":"mfr","etapeStatutId":"fai","paysId":"GF","surface":1},{"date":"2022-05-02","etapeTypeId":"mdp","etapeStatutId":"fai"},{"date":"2022-12-05","etapeTypeId":"mcr","etapeStatutId":"fav"},{"date":"2022-12-05","etapeTypeId":"asc","etapeStatutId":"fai"},{"date":"2022-12-05","etapeTypeId":"scl","etapeStatutId":"fai"},{"date":"2023-01-10","etapeTypeId":"apd","etapeStatutId":"fav"},{"date":"2023-01-24","etapeTypeId":"apo","etapeStatutId":"fav"},{"date":"2023-02-02","etapeTypeId":"dex","etapeStatutId":"acc","paysId":"GF","surface":1}]},{"id":22,"demarcheStatutId":"cls","demarchePublique":true,"etapes":[{"date":"2020-07-09","etapeTypeId":"mfr","etapeStatutId":"fai"},{"date":"2020-07-09","etapeTypeId":"mdp","etapeStatutId":"fai"},{"date":"2021-08-23","etapeTypeId":"css","etapeStatutId":"fai"}]}]